mcp_server_time/__init__.py
mcp_server_time/__main__.py
mcp_server_time/server.py
chungoid_mcp_server_time-0.6.2.dev3.dist-info/METADATA
chungoid_mcp_server_time-0.6.2.dev3.dist-info/WHEEL
chungoid_mcp_server_time-0.6.2.dev3.dist-info/entry_points.txt
chungoid_mcp_server_time-0.6.2.dev3.dist-info/RECORD
