Metadata-Version: 2.4
Name: chungoid-mcp-server-time
Version: 0.6.2.dev3
Summary: A Model Context Protocol server providing tools for working with time and dates
Author-email: Mariusz 'maledorak' Korzekwa <mariusz@korzekwa.dev>
License: MIT
Keywords: llm,mcp,time,timezone
Classifier: Development Status :: 4 - Beta
Classifier: Intended Audience :: Developers
Classifier: License :: OSI Approved :: MIT License
Classifier: Programming Language :: Python :: 3
Classifier: Programming Language :: Python :: 3.10
Requires-Python: >=3.10
Requires-Dist: mcp>=1.0.0
Requires-Dist: pydantic>=2.0.0
Requires-Dist: tzdata>=2024.2
